{"hash":"3619576cd0e111f404511a4de746b4deffa2cc58","data":{"metadata":{"siteName":"Gridsome Minimal Blog Starter","siteDescription":"A minimalist blog built with Gridsome"},"allPost":{"totalCount":4,"edges":[{"node":{"id":"15a1726811b204b414f51cf2b6848167","title":"zxcv한글만 asd","timeToRead":1,"description":"일단 만들어봐야지","date":"Apr 7 2020","path":"/zxcv-asd/"}},{"node":{"id":"0db2260508e50a7a1d472b88348d229f","title":"Third Post","timeToRead":1,"description":"third","date":"Jan 23 2020","path":"/third-post/"}},{"node":{"id":"56adb00a271429b54e8a27013b1ead3f","title":"Second Post","timeToRead":2,"description":"second post","date":"Dec 25 2019","path":"/second-post/"}},{"node":{"id":"7c7d1cd4afba7a45f253df7ffebdd813","title":"First Post","timeToRead":1,"description":"The first post written in Markdown","date":"Apr 20 2019","path":"/first-post/"}}]}},"context":{}}